{
  "session_id": "17b694bc",
  "user_message": "Bình thường thôi, chỉ bị chặt chém 200k có vậy",
  "detected_intent": "sarcasm",
  "audit_result": "PASS",
  "severity": "LOW",
  "violations": [
    {
      "rule": "no_empathy_for_sarcastic_user",
      "severity": "MEDIUM",
      "reason": "AI didn't show empathy when user was being sarcastic (disguised complaint)",
      "fix_suggestion": "Detect sarcasm and respond to underlying intent",
      "dimension": "emotional_awareness"
    }
  ],
  "persona_type": "gen_z",
  "emotional_state": null,
  "replayable": true
}